lumibot/__init__.py
lumibot/credentials.py
lumibot/backtesting/__init__.py
lumibot/backtesting/alpaca_backtesting.py
lumibot/backtesting/alpha_vantage_backtesting.py
lumibot/backtesting/backtesting_broker.py
lumibot/backtesting/ccxt_backtesting.py
lumibot/backtesting/pandas_backtesting.py
lumibot/backtesting/polygon_backtesting.py
lumibot/backtesting/thetadata_backtesting.py
lumibot/backtesting/yahoo_backtesting.py
lumibot/brokers/__init__.py
lumibot/brokers/alpaca.py
lumibot/brokers/broker.py
lumibot/brokers/ccxt.py
lumibot/brokers/example_broker.py
lumibot/brokers/interactive_brokers.py
lumibot/brokers/interactive_brokers_rest.py
lumibot/brokers/tradier.py
lumibot/data_sources/__init__.py
lumibot/data_sources/alpaca_data.py
lumibot/data_sources/alpha_vantage_data.py
lumibot/data_sources/ccxt_backtesting_data.py
lumibot/data_sources/ccxt_data.py
lumibot/data_sources/data_source.py
lumibot/data_sources/data_source_backtesting.py
lumibot/data_sources/example_broker_data.py
lumibot/data_sources/exceptions.py
lumibot/data_sources/interactive_brokers_data.py
lumibot/data_sources/interactive_brokers_rest_data.py
lumibot/data_sources/pandas_data.py
lumibot/data_sources/tradier_data.py
lumibot/data_sources/yahoo_data.py
lumibot/entities/__init__.py
lumibot/entities/asset.py
lumibot/entities/bar.py
lumibot/entities/bars.py
lumibot/entities/data.py
lumibot/entities/dataline.py
lumibot/entities/order.py
lumibot/entities/position.py
lumibot/entities/trading_fee.py
lumibot/example_strategies/__init__.py
lumibot/example_strategies/ccxt_backtesting_example.py
lumibot/example_strategies/crypto_important_functions.py
lumibot/example_strategies/lifecycle_logger.py
lumibot/example_strategies/options_hold_to_expiry.py
lumibot/example_strategies/simple_start_single_file.py
lumibot/example_strategies/stock_bracket.py
lumibot/example_strategies/stock_buy_and_hold.py
lumibot/example_strategies/stock_diversified_leverage.py
lumibot/example_strategies/stock_limit_and_trailing_stops.py
lumibot_jpmod-0.0.6.dist-info/LICENSE
lumibot_jpmod-0.0.6.dist-info/METADATA
lumibot_jpmod-0.0.6.dist-info/WHEEL
lumibot_jpmod-0.0.6.dist-info/top_level.txt
lumibot_jpmod-0.0.6.dist-info/RECORD
