Metadata-Version: 2.1
Name: lumibot_jpmod
Version: 0.0.6
Summary: Modded version of Lumiwealth library
Home-page: https://github.com/japoeder/lumibot
Author: Jonathan Poeder (orig: Robert Grzesik)
Author-email: japoeder@japoeder.com
Classifier: Programming Language :: Python :: 3
Classifier: License :: OSI Approved :: MIT License
Classifier: Operating System :: OS Independent
Requires-Python: >=3.9
License-File: LICENSE
Requires-Dist: polygon-api-client >=1.13.3
Requires-Dist: alpaca-py >=0.28.1
Requires-Dist: alpha-vantage
Requires-Dist: ibapi ==9.81.1.post1
Requires-Dist: yfinance >=0.2.46
Requires-Dist: matplotlib >=3.3.3
Requires-Dist: quandl
Requires-Dist: numpy <2,>=1.20.0
Requires-Dist: pandas >=2.2.0
Requires-Dist: pandas-datareader
Requires-Dist: pandas-market-calendars >=4.3.1
Requires-Dist: plotly >=5.18.0
Requires-Dist: flask >=2.2.2
Requires-Dist: sqlalchemy
Requires-Dist: flask-socketio
Requires-Dist: flask-sqlalchemy
Requires-Dist: flask-marshmallow
Requires-Dist: flask-security
Requires-Dist: marshmallow-sqlalchemy
Requires-Dist: email-validator
Requires-Dist: bcrypt
Requires-Dist: pytest
Requires-Dist: scipy >=1.13.0
Requires-Dist: ipython
Requires-Dist: quantstats-lumi >=0.3.3
Requires-Dist: python-dotenv
Requires-Dist: ccxt >=4.3.74
Requires-Dist: termcolor
Requires-Dist: jsonpickle
Requires-Dist: apscheduler ==3.10.4
Requires-Dist: appdirs
Requires-Dist: pyarrow
Requires-Dist: tqdm
Requires-Dist: lumiwealth-tradier >=0.1.12
Requires-Dist: pytz
Requires-Dist: psycopg2-binary
Requires-Dist: exchange-calendars >=4.5.2
Requires-Dist: duckdb
Requires-Dist: uuid
Requires-Dist: tabulate
Requires-Dist: thetadata
Requires-Dist: holidays
Requires-Dist: psutil
